ping_rs-2.0.1.dist-info/METADATA
ping_rs-2.0.1.dist-info/WHEEL
ping_rs-2.0.1.dist-info/licenses/LICENSE
ping_rs/__init__.py
ping_rs/_ping_rs.cpython-313-aarch64-linux-gnu.so
ping_rs/_ping_rs.pyi
ping_rs/core_schema.py
ping_rs/py.typed
ping_rs-2.0.1.dist-info/RECORD
