Metadata-Version: 2.4
Name: ping-rs
Version: 2.0.1
Classifier: Development Status :: 4 - Beta
Classifier: License :: OSI Approved :: MIT License
Classifier: Programming Language :: Python :: 3
Classifier: Programming Language :: Python :: 3.10
Classifier: Programming Language :: Python :: 3.11
Classifier: Programming Language :: Python :: 3.12
Classifier: Programming Language :: Python :: 3.13
Classifier: Programming Language :: Python :: 3.14
Classifier: Programming Language :: Rust
Classifier: Topic :: System :: Networking
Classifier: Topic :: System :: Monitoring
Classifier: Intended Audience :: Developers
Classifier: Intended Audience :: Information Technology
Classifier: Operating System :: POSIX :: Linux
Classifier: Operating System :: Microsoft :: Windows
Classifier: Operating System :: MacOS
Classifier: Typing :: Typed
License-File: LICENSE
Summary: Fast ping implementation using Rust with Python bindings
Keywords: ping,network,monitoring,rust,async
Author-email: a76yyyy <a76yyyy@gmail.com>
Requires-Python: >=3.10
Project-URL: Homepage, https://github.com/a76yyyy/ping-rs
Project-URL: Repository, https://github.com/a76yyyy/ping-rs
Project-URL: Source, https://github.com/a76yyyy/ping-rs
